{
  "best_players": [
    {
      "rang": 1,
      "nom prenom": "ezrzerzerz",
      "nombre de victoires": "541641"
    },
    {
      "rang": 2,
      "nom prenom": "ezrzerzerz",
      "nombre de victoires": "541641"
    },
    {
      "rang": 3,
      "nom prenom": "ezrzerzerz",
      "nombre de victoires": "541641"
    },
    {
      "rang": 4,
      "nom prenom": "ezrzerzerz",
      "nombre de victoires": "541641"
    },
    {
      "rang": 5,
      "nom prenom": "ezrzerzerz",
      "nombre de victoires": "541641"
    }
  ]
}

